vlconf/__init__.py
vlconf/verbosity.py
vlconf-2025.9.11.dist-info/METADATA
vlconf-2025.9.11.dist-info/WHEEL
vlconf-2025.9.11.dist-info/RECORD
